{
  "template": "https://github.com/collijk/python-package-cookiecutter",
  "commit": "a280cc423135620feceb7169e69d7188e7a7d075",
  "checkout": null,
  "context": {
    "cookiecutter": {
      "author_name": "James Collins",
      "author_email": "collijk1@gmail.com",
      "github_username": "collijk",
      "project_name": "rasterra",
      "project_slug": "rasterra",
      "package_name": "rasterra",
      "project_short_description": "A sleek, object-oriented interface designed for intuitive raster data manipulation in Python.",
      "_template": "https://github.com/collijk/python-package-cookiecutter"
    }
  },
  "directory": null
}
